l.py
draw_a_liukanshan-0.0.1.dist-info/LICENSE
draw_a_liukanshan-0.0.1.dist-info/METADATA
draw_a_liukanshan-0.0.1.dist-info/WHEEL
draw_a_liukanshan-0.0.1.dist-info/top_level.txt
draw_a_liukanshan-0.0.1.dist-info/RECORD
