Metadata-Version: 2.1
Name: draw-a-liukanshan
Version: 0.0.1
Summary: DONOT install this!
Author-email: Yun Dou <dixyes@gmail.com>
License: DO WHAT THE FUCK YOU WANT TO PUBLIC LICENSE
Project-URL: Homepage, https://github.com/dixyes/draw_a_liukanshan
Project-URL: Bug Tracker, https://github.com/dixyes/draw_a_liukanshan/issues
Classifier: Programming Language :: Python :: 3
Classifier: Operating System :: OS Independent
Requires-Python: >=3.0
License-File: LICENSE
